
{
  "result": {
    "list": [
      {
        "name": "皇家婴童金盏花婴儿清爽天然防晒乳40g天 天然儿清爽天然防。",
        "imgsrc": "http://image4.suning.cn/uimg/b2c/newcatentries/0000000000-000000000102632500_2_200x200.jpg?ver=2003",
        "curPrice": "500",
        "allnum": "300",
        "lastnum": "300",
        "datatype":0,
        "userName":"阿誉阿誉阿誉",
        "index":2

      },
      {
        "index":3,
        "name": "皇家婴童金盏花婴儿清爽天然防晒乳40g天 天然儿清爽天然防。",
        "imgsrc": "http://image4.suning.cn/uimg/b2c/newcatentries/0000000000-000000000102632500_2_200x200.jpg?ver=2003",
        "curPrice": "500",
        "allnum": "300",
        "lastnum": "300",
        "userName":"阿誉阿誉阿誉",
        "datatype":2

      },
      {
        "index":4,
        "name": "皇家婴童金盏花婴儿清爽天然防晒乳40g天 天然儿清爽天然防。",
        "imgsrc": "http://image4.suning.cn/uimg/b2c/newcatentries/0000000000-000000000102632500_2_200x200.jpg?ver=2003",
        "curPrice": "500",
        "allnum": "300",
        "lastnum": "300",
        "userName":"阿誉阿誉阿誉",
        "datatype":3


      },
      {
        "index":5,
        "name": "皇家婴童金盏花婴儿清爽天然防晒乳40g天 天然儿清爽天然防。",
        "imgsrc": "http://image4.suning.cn/uimg/b2c/newcatentries/0000000000-000000000102632500_2_200x200.jpg?ver=2003",
        "curPrice": "500",
        "allnum": "300",
        "lastnum": "300",
        "userName":"阿誉阿誉阿誉",
        "datatype":4

      },
      {
        "index":6,
        "name": "皇家婴童金盏花婴儿清爽天然防晒乳40g天 天然儿清爽天然防。",
        "imgsrc": "http://image4.suning.cn/uimg/b2c/newcatentries/0000000000-000000000102632500_2_200x200.jpg?ver=2003",
        "curPrice": "500",
        "allnum": "300",
        "lastnum": "300",
        "userName":"阿誉阿誉阿誉",
        "datatype":5


      },
      {
        "z-index":7,
        "name": "皇家婴童金盏花婴儿清爽天然防晒乳40g天 天然儿清爽天然防。",
        "imgsrc": "http://image4.suning.cn/uimg/b2c/newcatentries/0000000000-000000000102632500_2_200x200.jpg?ver=2003",
        "curPrice": "500",
        "allnum": "300",
        "lastnum": "300",
        "userName":"阿誉阿誉阿誉",
        "datatype":6

      },
      {
        "index":8,
        "name": "皇家婴童金盏花婴儿清爽天然防晒乳40g天 天然儿清爽天然防。",
        "imgsrc": "http://image4.suning.cn/uimg/b2c/newcatentries/0000000000-000000000102632500_2_200x200.jpg?ver=2003",
        "curPrice": "500",
        "allnum": "300",
        "lastnum": "300",
        "userName":"阿誉阿誉阿誉",
        "datatype":7


      },
      {
        "z-index":9,
        "name": "皇家婴童金盏花婴儿清爽天然防晒乳40g天 天然儿清爽天然防。",
        "imgsrc": "http://image4.suning.cn/uimg/b2c/newcatentries/0000000000-000000000102632500_2_200x200.jpg?ver=2003",
        "curPrice": "500",
        "allnum": "300",
        "lastnum": "300",
        "userName":"阿誉阿誉阿誉",
        "finish":true,
        "datatype":8

      },
      {
        "index":10,
        "name": "皇家婴童金盏花婴儿清爽天然防晒乳40g天 天然儿清爽天然防。",
        "imgsrc": "http://image4.suning.cn/uimg/b2c/newcatentries/0000000000-000000000102632500_2_200x200.jpg?ver=2003",
        "curPrice": "500",
        "allnum": "300",
        "lastnum": "300",
        "userName":"阿誉阿誉阿誉",
        "datatype":9


      },
      {
        "index":11,
        "name": "皇家婴童金盏花婴儿清爽天然防晒乳40g天 天然儿清爽天然防。",
        "imgsrc": "http://image4.suning.cn/uimg/b2c/newcatentries/0000000000-000000000102632500_2_200x200.jpg?ver=2003",
        "curPrice": "500",
        "allnum": "300",
        "lastnum": "300",
        "userName":"阿誉阿誉阿誉",
        "finish":false,
        "datatype":10

      }
    ],
    "totalpage":2
  }
}





